LICENSE
MANIFEST.in
README.rst
setup.py
betterforms/__init__.py
betterforms/changelist.py
betterforms/forms.py
betterforms/models.py
betterforms/multiform.py
betterforms/tests.py
betterforms/views.py
betterforms/templates/betterforms/field_as_div.html
betterforms/templates/betterforms/field_as_p.html
betterforms/templates/betterforms/fieldset_as_div.html
betterforms/templates/betterforms/fieldset_as_p.html
betterforms/templates/betterforms/form_as_fieldsets.html
betterforms/templates/betterforms/form_as_p.html
betterforms/templates/betterforms/sort_form_header.html
betterforms/templatetags/__init__.py
betterforms/templatetags/betterforms_tags.py
django_betterforms3.egg-info/PKG-INFO
django_betterforms3.egg-info/SOURCES.txt
django_betterforms3.egg-info/dependency_links.txt
django_betterforms3.egg-info/not-zip-safe
django_betterforms3.egg-info/requires.txt
django_betterforms3.egg-info/top_level.txt